coreason_mcp/__init__.py
coreason_mcp/aggregator.py
coreason_mcp/config.py
coreason_mcp/invocation_proxy.py
coreason_mcp/main.py
coreason_mcp/manager.py
coreason_mcp/registry.py
coreason_mcp/session_manager.py
coreason_mcp/types.py
coreason_mcp/utils/__init__.py
coreason_mcp/utils/logger.py
coreason_mcp-0.2.0.dist-info/METADATA
coreason_mcp-0.2.0.dist-info/WHEEL
coreason_mcp-0.2.0.dist-info/licenses/LICENSE
coreason_mcp-0.2.0.dist-info/licenses/NOTICE
coreason_mcp-0.2.0.dist-info/RECORD
