Metadata-Version: 2.4
Name: coreason_mcp
Version: 0.2.0
Summary: Standardizes external data access using the Model Context Protocol.
License: # The Prosperity Public License 3.0.0
License-File: LICENSE
License-File: NOTICE
Author: Gowtham A Rao
Author-email: gowtham.rao@coreason.ai
Requires-Python: >=3.11
Classifier: License :: Other/Proprietary License
Classifier: Programming Language :: Python :: 3.12
Classifier: Operating System :: OS Independent
Requires-Dist: httpx (>=0.28.1,<0.29.0)
Requires-Dist: jsonschema (>=4.25.1,<5.0.0)
Requires-Dist: loguru (>=0.7.2,<0.8.0)
Requires-Dist: mcp (>=1.25.0,<2.0.0)
Requires-Dist: pydantic (>=2.12.5,<3.0.0)
Project-URL: Documentation, https://github.com/CoReason-AI/coreason_mcp
Project-URL: Homepage, https://github.com/CoReason-AI/coreason_mcp
Project-URL: Repository, https://github.com/CoReason-AI/coreason_mcp
